README.rst
setup.cfg
setup.py
./LICENSE.txt
./README.rst
bin/consul-announcer
requirements/base.txt
requirements/test.txt
src/announcer/__init__.py
src/announcer/client.py
src/announcer/exceptions.py
src/announcer/service.py
src/announcer/utils.py
src/consul_announcer.egg-info/PKG-INFO
src/consul_announcer.egg-info/SOURCES.txt
src/consul_announcer.egg-info/dependency_links.txt
src/consul_announcer.egg-info/not-zip-safe
src/consul_announcer.egg-info/requires.txt
src/consul_announcer.egg-info/top_level.txt