Metadata-Version: 1.0
Name: consul-announcer
Version: 1.0.1
Summary: UNKNOWN
Home-page: https://github.com/ncbi/consul-announcer
Author: NCBI
Author-email: python-core@ncbi.nlm.nih.gov
License: NCBI license
Platform: UNKNOWN
